sugraph/__init__.py
sugraph/Algorithms/Flow.py
sugraph/Algorithms/ShortestPath.py
sugraph/Algorithms/Traversal.py
sugraph/Algorithms/__init__.py
sugraph/Data/Graph.py
sugraph/Data/IO.py
sugraph/Data/__init__.py
sugraph-0.1.0.dist-info/METADATA
sugraph-0.1.0.dist-info/WHEEL
sugraph-0.1.0.dist-info/top_level.txt
sugraph-0.1.0.dist-info/RECORD
