Metadata-Version: 2.2
Name: sugraph
Version: 0.1.0
Summary: A python package for graph analysis
Author-email: Umut Yunusoğlu <umut.yunusoglu@sabanciuniv.edu>
Classifier: Programming Language :: Python :: 3
Classifier: Operating System :: OS Independent
Requires-Python: >=3.6
Provides-Extra: dev
Requires-Dist: numpy; extra == "dev"
Requires-Dist: matplotlib; extra == "dev"
